ilensnewranks/__init__.py
ilensnewranks/add.py
ilensnewranks/subtract.py
ilensnewranks/extras/__init__.py
ilensnewranks/extras/multi.py
ilensnewranks-0.0.2.dist-info/METADATA
ilensnewranks-0.0.2.dist-info/WHEEL
ilensnewranks-0.0.2.dist-info/top_level.txt
ilensnewranks-0.0.2.dist-info/RECORD
